uacp/__init__.py
uacp/agent.py
uacp/db.py
uacp/schema.py
uacp/utils/__init__.py
uacp/utils/logger.py
uacp/utils/singleton.py
uacp-0.1.0.dist-info/LICENSE
uacp-0.1.0.dist-info/METADATA
uacp-0.1.0.dist-info/WHEEL
uacp-0.1.0.dist-info/RECORD
