Metadata-Version: 2.1
Name: uacp
Version: 0.1.0
Summary: Universal Agent Communication Protocol
Home-page: https://github.com/Undertone0809/uacp
License: MIT
Author: Undertone0809
Author-email: zeeland4work@gmail.com
Requires-Python: >=3.9,<4.0
Classifier: Development Status :: 3 - Alpha
Classifier: Intended Audience :: Developers
Classifier: License :: OSI Approved :: MIT License
Classifier: Operating System :: OS Independent
Classifier: Programming Language :: Python :: 3
Classifier: Programming Language :: Python :: 3.9
Classifier: Programming Language :: Python :: 3.10
Classifier: Programming Language :: Python :: 3.11
Classifier: Programming Language :: Python :: 3.12
Classifier: Topic :: Software Development :: Libraries :: Python Modules
Requires-Dist: pydantic (>=2.7.0,<3.0.0)
Project-URL: Repository, https://github.com/Undertone0809/uacp
